maqet/__init__.py
maqet/__main__.py
maqet/__version__.py
maqet/config_handlers.py
maqet/constants.py
maqet/decorators.py
maqet/error_messages.py
maqet/error_reporting.py
maqet/exceptions.py
maqet/formatters.py
maqet/logger.py
maqet/machine.py
maqet/maqet.py
maqet/os_interactions.py
maqet/process_spawner.py
maqet/snapshot.py
maqet/state_manager.py
maqet/storage.py
maqet/storage_registry.py
maqet/types.py
maqet/vm_lifecycle.py
maqet/vm_runner.py
maqet/api/__init__.py
maqet/api/decorators.py
maqet/api/metadata.py
maqet/api/provider.py
maqet/api/registry.py
maqet/config/__init__.py
maqet/config/manager.py
maqet/config/merger.py
maqet/config/parser.py
maqet/config/runtime_config.py
maqet/config/schema_validators.py
maqet/generators/__init__.py
maqet/generators/base_generator.py
maqet/generators/cli_generator.py
maqet/generators/python_generator.py
maqet/generators/rest_generator.py
maqet/ipc/__init__.py
maqet/ipc/retry.py
maqet/ipc/runner_client.py
maqet/ipc/unix_socket_server.py
maqet/managers/__init__.py
maqet/managers/config_manager.py
maqet/managers/process_lifecycle_manager.py
maqet/managers/qmp_manager.py
maqet/managers/vm_manager.py
maqet/protocols/__init__.py
maqet/protocols/ipc.py
maqet/protocols/process.py
maqet/protocols/qmp.py
maqet/protocols/state.py
maqet/protocols/storage.py
maqet/qmp/__init__.py
maqet/qmp/commands.py
maqet/qmp/keyboard.py
maqet/qmp/qmp.py
maqet/qmp/qmp_client.py
maqet/qmp/qmp_socket_client.py
maqet/security/__init__.py
maqet/security/validation.py
maqet/state/__init__.py
maqet/state/database_backup.py
maqet/state/migration_runner.py
maqet/state/vm_repository.py
maqet/utils/__init__.py
maqet/utils/error_files.py
maqet/utils/paths.py
maqet/utils/process_utils.py
maqet/utils/process_validation.py
maqet/utils/security.py
maqet/utils/subprocess_utils.py
maqet/utils/wait_conditions.py
maqet/utils/wait_logic.py
maqet/validation/__init__.py
maqet/validation/config_validator.py
maqet/vendor/__init__.py
maqet/vendor/qemu/__init__.py
maqet-0.0.15.dist-info/licenses/LICENSE
maqet-0.0.15.dist-info/METADATA
maqet-0.0.15.dist-info/WHEEL
maqet-0.0.15.dist-info/entry_points.txt
maqet-0.0.15.dist-info/top_level.txt
maqet-0.0.15.dist-info/RECORD
