Metadata-Version: 2.4
Name: maqet
Version: 0.0.15
Summary: M4x0n's QEMU Tool - A Python-based QEMU automation framework for VM running
Author: Max Rogol
Maintainer: Max Rogol
License-Expression: GPL-2.0-only
Project-URL: Repository, https://gitlab.com/m4x0n_24/maqet
Project-URL: Documentation, https://gitlab.com/m4x0n_24/maqet/blob/main/README.md
Project-URL: Issues, https://gitlab.com/m4x0n_24/maqet/issues
Keywords: qemu,virtualization,vm
Classifier: Development Status :: 4 - Beta
Classifier: Intended Audience :: Developers
Classifier: Intended Audience :: System Administrators
Classifier: Operating System :: POSIX :: Linux
Classifier: Programming Language :: Python :: 3
Classifier: Programming Language :: Python :: 3.12
Classifier: Programming Language :: Python :: 3.13
Classifier: Topic :: Software Development :: Testing
Classifier: Topic :: System :: Systems Administration
Classifier: Topic :: Utilities
Requires-Python: >=3.12
License-File: LICENSE
Requires-Dist: PyYAML>=6.0.2
Requires-Dist: psutil>=5.9.0
Provides-Extra: tables
Requires-Dist: tabulate>=0.9.0; extra == "tables"
Provides-Extra: docs
Requires-Dist: sphinx>=7.0; extra == "docs"
Requires-Dist: sphinx-rtd-theme>=2.0; extra == "docs"
Requires-Dist: myst-parser>=2.0; extra == "docs"
Provides-Extra: dev
Requires-Dist: pytest>=6.0; extra == "dev"
Requires-Dist: pytest-cov; extra == "dev"
Requires-Dist: pytest-testmon; extra == "dev"
Requires-Dist: pytest-xdist>=3.0; extra == "dev"
Requires-Dist: pytest-asyncio>=0.21.0; extra == "dev"
Requires-Dist: black; extra == "dev"
Requires-Dist: flake8; extra == "dev"
Requires-Dist: mypy; extra == "dev"
Requires-Dist: isort; extra == "dev"
Requires-Dist: pre-commit; extra == "dev"
Requires-Dist: ruff>=0.14.0; extra == "dev"
Requires-Dist: tabulate>=0.9.0; extra == "dev"
Requires-Dist: sphinx>=7.0; extra == "dev"
Requires-Dist: sphinx-rtd-theme>=2.0; extra == "dev"
Requires-Dist: myst-parser>=2.0; extra == "dev"
Dynamic: license-file
